[
    {
        "title":"Graphics Designing",
        "time":"FEB 2020 - JAN 2022",
        "description":"During the period i worked as a graphics designer in various social media pages. Mainly I created the template and various mockup for them.",
        "link":"/images/experiences/graphics.png"
    },
    {
        "title":"PR Manager",
        "time":"MAR 2020 - JAN 2021",
        "description":"I worked as a PR Manager in many social media pages, where I also maintained their online marketing",
        "link":"/images/experiences/pr.jpg"
    },
    {
        "title":"T-Shirt Designing",
        "time":"JAN 2021 - NOV 2021",
        "description":"During this 11 months I work as a T-Shirt designer in Bangali Anna social media page. Here I designed more than 100 tshirt designs",
        "link":"/images/experiences/tshirt.jpg"
    },
    {
        "title":"ML Model on Skin Cancer Detection",
        "time":"AUG 2022 - FEB 2023",
        "description":"It is a group project where we trying to create a ML model to detect skin cancer in early stage.Also this has published as a paper",
        "link":"/images/experiences/ml.webp"
    },
    {
        "title":"Campus Ambassador",
        "time":"DEC 2022 - JUN 2023",
        "description":"I was appointed as a campus ambassador of IIT Madras in our college campus. Here I learn about community building in first stage",
        "link":"/images/experiences/iitmadrash.jpeg"
    },
    {
        "title":"Blog Writing",
        "time":"JULY 2023 - Current",
        "description":"I started my journey on blog writing this year. Currently I posting my blogs on my Medium profile, mostly on machine learning and IoT based topics.",
        "link":"/images/experiences/medium.png"
    },
    {
        "title":"Core Member GDG Durgapur",
        "description":"I Worked as a graphics designer in GDG Durgapur for devfest 2023",
        "link":"/images/experiences/durg.jpg",
        "time":"SEP 2023 - NOV 2023"
    },
    {
        "title":"Intern Asiana Times",
        "description":"I was selected as a Graphic Designing intern in Asiana Times which is digital newspaper agency.",
        "link":"/images/achievements/asianatimes.jpeg",
        "time":"NOV 2023 - FEB 2024"
    },
    {
        "title":"Core Member H4B 3.0",
        "description":"I have selected as a core team member in graphics designing for Hack4Bengal 3.0",
        "link":"/images/achievements/h4b.jpeg",
        "time":"NOV 2023 - Current"
    }
]